web_bot_auth/__init__.py
web_bot_auth/_modidx.py
web_bot_auth/core.py
web_bot_auth-0.0.1.dist-info/licenses/LICENSE
web_bot_auth-0.0.1.dist-info/METADATA
web_bot_auth-0.0.1.dist-info/WHEEL
web_bot_auth-0.0.1.dist-info/entry_points.txt
web_bot_auth-0.0.1.dist-info/top_level.txt
web_bot_auth-0.0.1.dist-info/RECORD
